chainlibpy/__init__.py
chainlibpy/amino/__init__.py
chainlibpy/amino/basic.py
chainlibpy/amino/message.py
chainlibpy/amino/signdoc.py
chainlibpy/amino/tx.py
chainlibpy/cro_coin.py
chainlibpy/generated/__init__.py
chainlibpy/generated/common.py
chainlibpy/grpc_client.py
chainlibpy/py.typed
chainlibpy/transaction.py
chainlibpy/utils/__init__.py
chainlibpy/utils/types.py
chainlibpy/wallet.py
chainlibpy-3.0.0.dist-info/LICENSE
chainlibpy-3.0.0.dist-info/WHEEL
chainlibpy-3.0.0.dist-info/METADATA
chainlibpy-3.0.0.dist-info/RECORD
