Metadata-Version: 2.1
Name: chainlibpy
Version: 3.0.0
Summary: Tools for Crypto.org Chain wallet management and offline transaction signing
Home-page: https://github.com/crypto-org-chain/chainlibpy
License: Apache-2.0
Keywords: CRO,blockchain,signature,crypto.org
Author: chain-dev-team
Author-email: chain@crypto.org
Requires-Python: >=3.8,<4.0
Classifier: Intended Audience :: Developers
Classifier: License :: OSI Approved :: Apache Software License
Classifier: Programming Language :: Python :: 3
Classifier: Programming Language :: Python :: 3.10
Classifier: Programming Language :: Python :: 3.8
Classifier: Programming Language :: Python :: 3.9
Classifier: Topic :: Software Development :: Libraries :: Python Modules
Project-URL: Repository, https://github.com/crypto-org-chain/chainlibpy
